aiohttp_apispec/__init__.py
aiohttp_apispec/aiohttp_apispec.py
aiohttp_apispec/decorators.py
aiohttp_apispec/middlewares.py
aiohttp_apispec/utils.py
aiohttp_apispec-0.7.6.dist-info/LICENSE
aiohttp_apispec-0.7.6.dist-info/METADATA
aiohttp_apispec-0.7.6.dist-info/WHEEL
aiohttp_apispec-0.7.6.dist-info/top_level.txt
aiohttp_apispec-0.7.6.dist-info/RECORD
