Metadata-Version: 2.1
Name: aiohttp-apispec
Version: 0.7.6
Summary: Build and document REST APIs with aiohttp and apispec
Home-page: https://github.com/maximdanilchenko/aiohttp-apispec
Author: Danilchenko Maksim
Author-email: dmax.dev@gmail.com
License: MIT
Keywords: aiohttp marshmallow apispec swagger
Platform: UNKNOWN
Classifier: Development Status :: 3 - Alpha
Classifier: Intended Audience :: Developers
Classifier: License :: OSI Approved :: MIT License
Classifier: Natural Language :: English
Classifier: Programming Language :: Python :: 3.5
Classifier: Programming Language :: Python :: 3.6
Classifier: Programming Language :: Python :: 3.7
Requires-Dist: aiohttp (<=3.4.4)
Requires-Dist: apispec (<=0.39.0)
Requires-Dist: webargs (<=4.1.0)
